Workbook

Sheet Sheet1
A1: Column1 | B1: Update_region | C1: Region | D1: Category | E1: sales | F1: discount | G1: quantity | H1: order_date | I1: delivery_date | J1: customer_type | K1: customer_type2 | L1: payment_mode | M1: profit | N1: Update_city | O1: city | P1: Profit Margin | Q1: Updates_city | R1: Updated_region
A2: ORD100000 | B2: East | C2: East | D2: Clothing | E2: 713.49 | F2: 0.31 | G2: 3 | H2: 45015 | I2: 45017 | J2: Member | K2: Member | L2: UPI | M2: 114.72 | N2: Bangalore | O2: Bangalore | P2: =Sheet1!$M2/Sheet1!$E2 -> 0.16078712 | Q2: Bangalore | R2: East
A3: ORD100001 | B3: West | C3: Wset | D3: Electronics | E3: 3802.97 | F3: 0.38 | G3: 4 | H3: 45166 | I3: 45172 | J3: Regular | K3: Regular | L3: Card | M3: 971.41 | N3: Mumbai | O3: MUMBAI | P3: =Sheet1!$M3/Sheet1!$E3 -> 0.25543457 | Q3: Mumbai | R3: West
A4: ORD100002 | B4: South | C4: North | D4: Home Care | E4: 3588.97 | F4: 0.1 | G4: 7 | H4: 45360 | I4: 45366 | J4: Regular | K4: Regular | L4: Cash | M4: 769.08 | N4: Pune | O4: Pune | P4: =Sheet1!$M4/Sheet1!$E4 -> 0.21428989 | Q4: Pune | R4: North
A5: ORD100003 | B5: North | C5: South | D5: Electronics | E5: 1160.86 | F5: 0.27 | G5: 5 | H5: 45578 | I5: 45584 | J5: Member | K5: Member | L5: UPI | M5: 71.61 | N5: Hyderabad | O5: hyderabad | P5: =Sheet1!$M5/Sheet1!$E5 -> 0.061687025 | Q5: Hyderabad | R5: South
A6: ORD100004 | B6: East | C6: East | D6: Electronics | E6: 3071.32 | F6: 0 | G6: 7 | H6: 45022 | I6: 45025 | J6: New | K6: New | L6: Cash | M6: 621.92 | N6: Bangalore | O6: Bangalore | P6: =Sheet1!$M6/Sheet1!$E6 -> 0.20249274 | Q6: Bangalore | R6: East
A7: ORD100005 | B7: West | C7: Wset | D7: Grocery | E7: 2566.18 | F7: 0.02 | G7: 6 | H7: 45108 | I7: 45111 | J7: Member | K7: Member | L7: UPI | M7: 578.94 | N7: Hyderabad | O7: Hyderabad | P7: =Sheet1!$M7/Sheet1!$E7 -> 0.22560382 | Q7: Hyderabad | R7: West
A8: ORD100006 | B8: South | C8: North | D8: Personal Care | E8: 398 | F8: 0.16 | G8: 4 | H8: 45119 | I8: 45124 | J8: New | K8: New | L8: Cash | M8: 110.31 | N8: Bangalore | O8: Bangalore | P8: =Sheet1!$M8/Sheet1!$E8 -> 0.2771608 | Q8: Bangalore | R8: North
A9: ORD100007 | B9: North | C9: South | D9: Personal Care | E9: 1462.95 | F9: 0.23 | G9: 2 | H9: 45064 | I9: 45066 | J9: Regular | K9: Regular | L9: UPI | M9: 91.68 | N9: Pune | O9: pune | P9: =Sheet1!$M9/Sheet1!$E9 -> 0.062667897 | Q9: Pune | R9: South
A10: ORD100008 | B10: East | C10: East | D10: Personal Care | E10: 4997.47 | F10: 0.29 | G10: 6 | H10: 45296 | I10: 45299 | J10: Regular | K10: Regular | L10: Card | M10: 995.78 | N10: Chennai | O10: Chennai | P10: =Sheet1!$M10/Sheet1!$E10 -> 0.19925682 | Q10: Chennai | R10: East
A11: ORD100009 | B11: West | C11: Wset | D11: Grocery | E11: 587.72 | F11: 0.44 | G11: 6 | H11: 45514 | I11: 45521 | J11: New | K11: New | L11: Cash | M11: 102.96 | N11: Mumbai | O11: MUMBAI | P11: =Sheet1!$M11/Sheet1!$E11 -> 0.17518546 | Q11: Mumbai | R11: West
A12: ORD100010 | B12: South | C12: North | D12: Clothing | E12: 2581.42 | F12: 0.39 | G12: 6 | H12: 45419 | I12: 45420 | J12: Regular | K12: Regular | L12: Cash | M12: 542.82 | N12: Chennai | O12: chennai | P12: =Sheet1!$M12/Sheet1!$E12 -> 0.21027961 | Q12: Chennai | R12: North
A13: ORD100011 | B13: North | C13: South | D13: Clothing | E13: 4261.74 | F13: 0.15 | G13: 1 | H13: 45171 | I13: 45172 | J13: New | K13: New | L13: UPI | M13: 1028.47 | N13: Chennai | O13: Chennai | P13: =Sheet1!$M13/Sheet1!$E13 -> 0.24132631 | Q13: Chennai | R13: South
... A499: ORD100497 | B499: West | C499: Wset | D499: Grocery | E499: 1550.13 | F499: 0.02 | G499: 3 | H499: 45170 | I499: 45172 | J499: Member | K499: Member | L499: UPI | M499: 343.75 | N499: Bangalore | O499: bangalore | P499: =Sheet1!$M499/Sheet1!$E499 -> 0.22175559 | Q499: Bangalore | R499: West
